[
    {
        "src":"https://img09.yesmyimg.com/n/641/214/6214641/8031696_110x180.png",
        "des":"【名庄】玛姆红带香槟(天然酒)↵G H Mumm Cordon Rouge",
        "price": "299.0",
        "sell":"420"
        
    },
    {
        "src": "https://img18.yesmyimg.com/5193653/4853503_110x180.jpg",
        "des":"【名庄】龙船酒庄红葡萄酒2008↵Chateau Beychevelle",
        "price":"1029.0",
        "sell":"109"
        
    },
    {
        "src":"https://img19.yesmyimg.com/n/970/239/6239970/3742382_110x180.png",
        "des":"【名庄】雄狮露儿侯爵干红葡萄酒2010↵Clos Du Marquis Saint-Julien2010",
        "price":"599.0",
        "sell":"105"
        
    },
    {
        "src":"https://img19.yesmyimg.com/n/729/241/6241729/5672714_110x180.jpg",
        "des":"【名庄】宝得根庄园干红葡萄酒2011年750ml↵Pontet Canet 2011",
        "price":"868.0",
        "sell":"16"
        
    },
    {
        "src":"https://img18.yesmyimg.com/n/886/242/6242886/7181791_110x180.JPG",
        "des":"荔仙庄园干红葡萄酒2010年750ml↵Chateau Prieure Lichine",
        "price":"578.0",
        "sell":"5"
    }

]


